{"version":1,"viewport":{"width":1200,"height":800},"buffers":{"100":{"data":[-0.3,0.0,0.3,43.0,0.7,0.0,1.3,30.0,1.7,0.0,2.3,28.0,2.7,0.0,3.3,52.0,3.7,0.0,4.3,52.0,4.7,0.0,5.3,53.0,5.7,0.0,6.3,54.0,6.7,0.0,7.3,43.0,7.7,0.0,8.3,29.0,8.7,0.0,9.3,14.0,9.7,0.0,10.3,15.0,10.7,0.0,11.3,16.0]},"110":{"data":[-0.3,0.0,0.3,7.9,0.7,0.0,1.3,5.9,1.7,0.0,2.3,5.0,2.7,0.0,3.3,5.6,3.7,0.0,4.3,5.4,4.7,0.0,5.3,6.9,5.7,0.0,6.3,4.0,6.7,0.0,7.3,10.5,7.7,0.0,8.3,7.1,8.7,0.0,9.3,9.5,9.7,0.0,10.3,6.3,10.7,0.0,11.3,7.8]},"120":{"data":[-0.3,0.0,0.3,49375.02,0.7,0.0,1.3,35202.5,1.7,0.0,2.3,77892.5,2.7,0.0,3.3,50191.4,3.7,0.0,4.3,69088.4,4.7,0.0,5.3,59829.7,5.7,0.0,6.3,93047.5,6.7,0.0,7.3,35860.5,7.7,0.0,8.3,45554.0,8.7,0.0,9.3,17826.4,9.7,0.0,10.3,55375.0,10.7,0.0,11.3,52270.0]}},"transforms":{"50":{"sx":0.141065831,"sy":0.03030303,"tx":-0.775862069,"ty":-0.818181818},"51":{"sx":0.141065831,"sy":0.155844156,"tx":-0.775862069,"ty":-0.818181818},"52":{"sx":0.141065831,"sy":1.7586e-05,"tx":-0.775862069,"ty":-0.818181818}},"panes":{"1":{"name":"POCount","region":{"clipYMin":0.05,"clipYMax":0.95,"clipXMin":-0.95,"clipXMax":-0.35},"hasClearColor":true,"clearColor":[0.07,0.09,0.14,1.0]},"2":{"name":"LeadTime","region":{"clipYMin":0.05,"clipYMax":0.95,"clipXMin":-0.3,"clipXMax":0.3},"hasClearColor":true,"clearColor":[0.07,0.09,0.14,1.0]},"3":{"name":"TotalCost","region":{"clipYMin":0.05,"clipYMax":0.95,"clipXMin":0.35,"clipXMax":0.95},"hasClearColor":true,"clearColor":[0.07,0.09,0.14,1.0]}},"layers":{"10":{"paneId":1,"name":"po"},"20":{"paneId":2,"name":"lead"},"30":{"paneId":3,"name":"cost"}},"geometries":{"101":{"vertexBufferId":100,"format":"rect4","vertexCount":12},"111":{"vertexBufferId":110,"format":"rect4","vertexCount":12},"121":{"vertexBufferId":120,"format":"rect4","vertexCount":12}},"drawItems":{"102":{"layerId":10,"name":"po-bars","pipeline":"instancedRect@1","geometryId":101,"transformId":50,"color":[0.23137254901960785,0.5098039215686274,0.9647058823529412,1.0],"cornerRadius":2.0},"112":{"layerId":20,"name":"lead-bars","pipeline":"instancedRect@1","geometryId":111,"transformId":51,"color":[0.9607843137254902,0.6196078431372549,0.043137254901960784,1.0],"cornerRadius":2.0},"122":{"layerId":30,"name":"cost-bars","pipeline":"instancedRect@1","geometryId":121,"transformId":52,"color":[0.9372549019607843,0.26666666666666666,0.26666666666666666,1.0],"cornerRadius":2.0}},"textOverlay":{"fontSize":13,"color":"#b2b5bc","labels":[{"clipX":-0.65,"clipY":0.98,"text":"PO Count","align":"c"},{"clipX":0.0,"clipY":0.98,"text":"Avg Lead Time (days)","align":"c"},{"clipX":0.65,"clipY":0.98,"text":"Total Cost ($)","align":"c"}]}}